lava_serpent/__init__.py
lava_serpent/__main__.py
lava_serpent/cli.py
lava_serpent/lava_manifest.py
lava_serpent/packer.py
lava_serpent/unpacker.py
lava_serpent-0.1.2.dist-info/METADATA
lava_serpent-0.1.2.dist-info/WHEEL
lava_serpent-0.1.2.dist-info/entry_points.txt
lava_serpent-0.1.2.dist-info/RECORD
