Metadata-Version: 2.3
Name: lava-serpent
Version: 0.1.2
Summary: 
Author: alexstrnik
Author-email: alex.str.nik@gmail.com
Requires-Python: >=3.9
Classifier: Programming Language :: Python :: 3
Classifier: Programming Language :: Python :: 3.9
Classifier: Programming Language :: Python :: 3.10
Classifier: Programming Language :: Python :: 3.11
Classifier: Programming Language :: Python :: 3.12
Classifier: Programming Language :: Python :: 3.13
Requires-Dist: pillow (>=11.2.1,<12.0.0)
Requires-Dist: pillow-avif-plugin (>=1.5.2,<2.0.0)
Requires-Dist: rectangle-packer (>=2.0.4,<3.0.0)
